housenumparser/__init__.py
housenumparser/element.py
housenumparser/merger.py
housenumparser/reader.py
housenumparser-0.1.2.dist-info/LICENSE
housenumparser-0.1.2.dist-info/METADATA
housenumparser-0.1.2.dist-info/WHEEL
housenumparser-0.1.2.dist-info/top_level.txt
housenumparser-0.1.2.dist-info/RECORD
