Metadata-Version: 2.1
Name: housenumparser
Version: 0.1.2
Summary: housenum_be_r_parser
Home-page: http://github.com/onroerenderfgoed/housenum-be-r-parser
Author: Onroerend Erfgoed
Author-email: ict@onroerenderfgoed.be
License: MIT
Platform: UNKNOWN
Classifier: Development Status :: 4 - Beta
Classifier: Intended Audience :: Developers
Classifier: Natural Language :: English
Classifier: License :: OSI Approved :: MIT License
Classifier: Operating System :: OS Independent
Classifier: Programming Language :: Python
Classifier: Programming Language :: Python :: 2.7
Classifier: Programming Language :: Python :: 3.5
Classifier: Programming Language :: Python :: 3.6
Requires-Dist: enum34 ; python_version < "3.4"
